Metadata-Version: 1.0
Name: vi-dist
Version: 0.1
Summary: Distributions
Home-page: UNKNOWN
Author: UNKNOWN
Author-email: UNKNOWN
License: UNKNOWN
Platform: UNKNOWN
